<?xml version="1.0" encoding="utf-8"?>
<DriverPackCatalog schemaVersion="1" generatedAtUtc="2026-05-03T05:49:49Z" totalItems="17" category="WinPE">
  <Metadata name="Foundry Unified WinPE Catalog" description="Normalized WinPE catalog containing driver packs from Dell, HP, Lenovo, Microsoft, and Intel" />
  <Sources>
    <Source manufacturer="Dell" catalogUrl="https://downloads.dell.com/catalog/DriverPackCatalog.cab" lastUpdated="2026-03-31T00:00:00Z" itemCount="9" />
    <Source manufacturer="HP" catalogUrl="https://hpia.hpcloud.hp.com/downloads/driverpackcatalog/HPClientDriverPackCatalog.cab" lastUpdated="2026-04-30T00:00:00Z" itemCount="7" />
    <Source manufacturer="Intel" catalogUrl="https://www.intel.com/content/www/us/en/download/18231/intel-proset-wireless-software-and-wi-fi-drivers-for-it-administrators.html" lastUpdated="2026-03-24T00:00:00Z" itemCount="1" />
  </Sources>
  <DriverPacks>
    <DriverPack id="524P6|x86" packageId="524P6" manufacturer="Dell" name="WinPE10.0-Drivers-A39-524P6.cab" version="A39" fileName="WinPE10.0-Drivers-A39-524P6.cab" downloadUrl="https://downloads.dell.com/FOLDER14364021M/1/WinPE10.0-Drivers-A39-524P6.cab" sizeBytes="141010161" format="cab" type="WinPE" packageRole="BaseDriverPack" releaseDate="2026-03-31">
      <OsInfo name="WinPE" releaseId="10" architecture="x86" />
      <Hashes md5="13d1360debfc2e539bc8e04d9daa0c97" sha256="8b4f308a2ec886f7421b5f9a2ca97f25c89af1fb6aa7631bb42bbc52531ab924" />
    </DriverPack>
    <DriverPack id="524P6|x64" packageId="524P6" manufacturer="Dell" name="WinPE10.0-Drivers-A39-524P6.cab" version="A39" fileName="WinPE10.0-Drivers-A39-524P6.cab" downloadUrl="https://downloads.dell.com/FOLDER14364021M/1/WinPE10.0-Drivers-A39-524P6.cab" sizeBytes="141010161" format="cab" type="WinPE" packageRole="BaseDriverPack" releaseDate="2026-03-31">
      <OsInfo name="WinPE" releaseId="10" architecture="x64" />
      <Hashes md5="13d1360debfc2e539bc8e04d9daa0c97" sha256="8b4f308a2ec886f7421b5f9a2ca97f25c89af1fb6aa7631bb42bbc52531ab924" />
    </DriverPack>
    <DriverPack id="RV5X6" packageId="RV5X6" manufacturer="Dell" name="WinPE11.0-Drivers-A09-RV5X6.cab" version="A09" fileName="WinPE11.0-Drivers-A09-RV5X6.cab" downloadUrl="https://downloads.dell.com/FOLDER14306791M/1/WinPE11.0-Drivers-A09-RV5X6.cab" sizeBytes="33323695" format="cab" type="WinPE" packageRole="BaseDriverPack" releaseDate="2026-03-31">
      <OsInfo name="WinPE" releaseId="11" architecture="x64" />
      <Hashes md5="6236fe86066aa0dea14358dfd95869f4" sha256="542ad63ecabd48ad8aeb59e2c29ec38012459bc209086f5ceae7a27178fa4291" />
    </DriverPack>
    <DriverPack id="MJ53D|x64" packageId="MJ53D" manufacturer="Dell" name="WinPE3.0-Drivers-A23-MJ53D.CAB" version="A23" fileName="WinPE3.0-Drivers-A23-MJ53D.CAB" downloadUrl="https://downloads.dell.com/FOLDER05323227M/1/WinPE3.0-Drivers-A23-MJ53D.CAB" sizeBytes="179684132" format="cab" type="WinPE" packageRole="BaseDriverPack" releaseDate="2018-11-21">
      <OsInfo name="WinPE" releaseId="3" architecture="x64" />
      <Hashes md5="87FC2363BF818266A20964E0AB64C993" sha256="9B289DD44259A8E3F8A67BE22FCC5A00F9CB36F723D990228258E8D4573A9085" />
    </DriverPack>
    <DriverPack id="MJ53D|x86" packageId="MJ53D" manufacturer="Dell" name="WinPE3.0-Drivers-A23-MJ53D.CAB" version="A23" fileName="WinPE3.0-Drivers-A23-MJ53D.CAB" downloadUrl="https://downloads.dell.com/FOLDER05323227M/1/WinPE3.0-Drivers-A23-MJ53D.CAB" sizeBytes="179684132" format="cab" type="WinPE" packageRole="BaseDriverPack" releaseDate="2018-11-21">
      <OsInfo name="WinPE" releaseId="3" architecture="x86" />
      <Hashes md5="87FC2363BF818266A20964E0AB64C993" sha256="9B289DD44259A8E3F8A67BE22FCC5A00F9CB36F723D990228258E8D4573A9085" />
    </DriverPack>
    <DriverPack id="F1YJC|x86" packageId="F1YJC" manufacturer="Dell" name="WinPE4.0-Drivers-A06-F1YJC.CAB" version="A06" fileName="WinPE4.0-Drivers-A06-F1YJC.CAB" downloadUrl="https://downloads.dell.com/FOLDER03048988M/1/WinPE4.0-Drivers-A06-F1YJC.CAB" sizeBytes="14122848" format="cab" type="WinPE" packageRole="BaseDriverPack" releaseDate="2015-06-02">
      <OsInfo name="WinPE" releaseId="4" architecture="x86" />
      <Hashes md5="96DAA271FB10208B464FBD98E83C0528" sha256="CFA582D6753A914EA4ED94FA8DB9B389097FF28F6145BEFE9796C2157B1F366B" />
    </DriverPack>
    <DriverPack id="F1YJC|x64" packageId="F1YJC" manufacturer="Dell" name="WinPE4.0-Drivers-A06-F1YJC.CAB" version="A06" fileName="WinPE4.0-Drivers-A06-F1YJC.CAB" downloadUrl="https://downloads.dell.com/FOLDER03048988M/1/WinPE4.0-Drivers-A06-F1YJC.CAB" sizeBytes="14122848" format="cab" type="WinPE" packageRole="BaseDriverPack" releaseDate="2015-06-02">
      <OsInfo name="WinPE" releaseId="4" architecture="x64" />
      <Hashes md5="96DAA271FB10208B464FBD98E83C0528" sha256="CFA582D6753A914EA4ED94FA8DB9B389097FF28F6145BEFE9796C2157B1F366B" />
    </DriverPack>
    <DriverPack id="2F5W2|x86" packageId="2F5W2" manufacturer="Dell" name="WinPE5.0-Drivers-A10-2F5W2.CAB" version="A10" fileName="WinPE5.0-Drivers-A10-2F5W2.CAB" downloadUrl="https://downloads.dell.com/FOLDER04560673M/1/WinPE5.0-Drivers-A10-2F5W2.CAB" sizeBytes="103883414" format="cab" type="WinPE" packageRole="BaseDriverPack" releaseDate="2017-11-30">
      <OsInfo name="WinPE" releaseId="5" architecture="x86" />
      <Hashes md5="43AA87C03D61206CA4E7324F16954CE6" sha256="DA2F295C64DA5D4592DCC59623F19DAF2E1CCA3BB964759AD3B578915F634B6A" />
    </DriverPack>
    <DriverPack id="2F5W2|x64" packageId="2F5W2" manufacturer="Dell" name="WinPE5.0-Drivers-A10-2F5W2.CAB" version="A10" fileName="WinPE5.0-Drivers-A10-2F5W2.CAB" downloadUrl="https://downloads.dell.com/FOLDER04560673M/1/WinPE5.0-Drivers-A10-2F5W2.CAB" sizeBytes="103883414" format="cab" type="WinPE" packageRole="BaseDriverPack" releaseDate="2017-11-30">
      <OsInfo name="WinPE" releaseId="5" architecture="x64" />
      <Hashes md5="43AA87C03D61206CA4E7324F16954CE6" sha256="DA2F295C64DA5D4592DCC59623F19DAF2E1CCA3BB964759AD3B578915F634B6A" />
    </DriverPack>
    <DriverPack id="sp155634" packageId="sp155634" manufacturer="HP" name="sp155634" version="3.00" fileName="sp155634.exe" downloadUrl="https://ftp.ext.hp.com/pub/softpaq/sp155501-156000/sp155634.exe" format="exe" type="WinPE" packageRole="BaseDriverPack" releaseDate="2024-11-12">
      <OsInfo name="WinPE" releaseId="10/11" architecture="x64" />
    </DriverPack>
    <DriverPack id="sp161830" packageId="sp161830" manufacturer="HP" name="sp161830" version="3.10" fileName="sp161830.exe" downloadUrl="https://ftp.ext.hp.com/pub/softpaq/sp161501-162000/sp161830.exe" format="exe" type="WinPE" packageRole="BaseDriverPack" releaseDate="2025-08-22">
      <OsInfo name="WinPE" releaseId="10/11" architecture="x64" />
    </DriverPack>
    <DriverPack id="sp165773" packageId="sp165773" manufacturer="HP" name="sp165773" version="3.20" fileName="sp165773.exe" downloadUrl="https://ftp.ext.hp.com/pub/softpaq/sp165501-166000/sp165773.exe" format="exe" type="WinPE" packageRole="BaseDriverPack" releaseDate="2025-12-17">
      <OsInfo name="WinPE" releaseId="10/11" architecture="x64" />
    </DriverPack>
    <DriverPack id="sp172442" packageId="sp172442" manufacturer="HP" name="sp172442" version="3.30" fileName="sp172442.exe" downloadUrl="https://ftp.ext.hp.com/pub/softpaq/sp172001-172500/sp172442.exe" format="exe" type="WinPE" packageRole="BaseDriverPack" releaseDate="2026-04-30">
      <OsInfo name="WinPE" releaseId="10/11" architecture="x64" />
    </DriverPack>
    <DriverPack id="sp64529" packageId="sp64529" manufacturer="HP" name="sp64529" version="1.01" fileName="sp64529.exe" downloadUrl="https://ftp.hp.com/pub/softpaq/sp64501-65000/sp64529.exe" format="exe" type="WinPE" packageRole="BaseDriverPack" releaseDate="2013-12-04">
      <OsInfo name="WinPE" releaseId="4" architecture="x64" />
    </DriverPack>
    <DriverPack id="sp71912" packageId="sp71912" manufacturer="HP" name="sp71912" version="1.03" fileName="sp71912.exe" downloadUrl="https://ftp.hp.com/pub/softpaq/sp71501-72000/sp71912.exe" format="exe" type="WinPE" packageRole="BaseDriverPack" releaseDate="2015-09-14">
      <OsInfo name="WinPE" releaseId="5" architecture="x64" />
    </DriverPack>
    <DriverPack id="sp87510" packageId="sp87510" manufacturer="HP" name="sp87510" version="1.07" fileName="sp87510.exe" downloadUrl="https://ftp.hp.com/pub/softpaq/sp87501-88000/sp87510.exe" format="exe" type="WinPE" packageRole="BaseDriverPack" releaseDate="2018-05-30">
      <OsInfo name="WinPE" releaseId="3" architecture="x64" />
    </DriverPack>
    <DriverPack id="intel-wireless-winre-x64" packageId="intel-wireless-winre-x64" manufacturer="Intel" name="Intel Wireless Wi-Fi Drivers for IT Administrators" version="24.30.1" fileName="WiFi-24.30.1-Driver64-Win10-Win11.zip" downloadUrl="https://downloadmirror.intel.com/915923/WiFi-24.30.1-Driver64-Win10-Win11.zip" format="zip" type="WinPE" packageRole="WifiSupplement" driverFamily="IntelWireless" releaseDate="2026-03-24">
      <OsInfo name="WinPE" releaseId="11" architecture="x64" />
      <Hashes sha256="A09AF2CC6E6305E395A553C4CDE4264F554DC7DF29EEF34DBBDE53025464EF8E" />
    </DriverPack>
  </DriverPacks>
</DriverPackCatalog>